{"v":"4.8.0","meta":{"g":"LottieFiles AE 3.5.9","a":"","k":"","d":"","tc":""},"fr":60,"ip":22,"op":470,"w":1500,"h":1500,"nm":"לוגו דיבור Lottie","ddd":0,"assets":[],"layers":[{"ddd":0,"ind":1,"ty":4,"nm":"Volume L","sr":1,"ks":{"o":{"a":0,"k":100,"ix":11},"r":{"a":0,"k":0,"ix":10},"p":{"a":0,"k":[503.691,692,0],"ix":2},"a":{"a":0,"k":[0.691,-58,0],"ix":1},"s":{"a":0,"k":[100,100,100],"ix":6}},"ao":0,"shapes":[{"ty":"gr","it":[{"ty":"rc","d":1,"s":{"a":1,"k":[{"i":{"x":[0.667,0.667],"y":[1,1]},"o":{"x":[0.333,0.333],"y":[0,0]},"t":21.852,"s":[170.375,170.375]},{"i":{"x":[0.667,0.667],"y":[1,1]},"o":{"x":[0.333,0.333],"y":[0,0]},"t":36.746,"s":[170.375,405.375]},{"i":{"x":[0.667,0.667],"y":[1,1]},"o":{"x":[0.333,0.333],"y":[0,0]},"t":51.686,"s":[170.375,225.375]},{"i":{"x":[0.833,0.833],"y":[1,0.833]},"o":{"x":[0.333,0.333],"y":[0,0]},"t":66.543,"s":[170.375,422.375]},{"i":{"x":[0.667,0.667],"y":[1,1]},"o":{"x":[0.167,0.167],"y":[0,0.167]},"t":81.441,"s":[170.375,222.084]},{"i":{"x":[0.667,0.667],"y":[1,1]},"o":{"x":[0.333,0.333],"y":[0,0]},"t":96.336,"s":[170.375,493.375]},{"i":{"x":[0.667,0.667],"y":[1,1]},"o":{"x":[0.333,0.333],"y":[0,0]},"t":111.438,"s":[170.375,250.375]},{"i":{"x":[0.667,0.667],"y":[1,1]},"o":{"x":[0.333,0.333],"y":[0,0]},"t":126.133,"s":[170.375,446.375]},{"i":{"x":[0.667,0.667],"y":[1,1]},"o":{"x":[0.333,0.333],"y":[0,0]},"t":145.645,"s":[170.375,249.875]},{"i":{"x":[0.667,0.667],"y":[1,1]},"o":{"x":[0.333,0.333],"y":[0,0]},"t":159.82,"s":[170.375,428.375]},{"i":{"x":[0.667,0.667],"y":[1,1]},"o":{"x":[0.333,0.333],"y":[0,0]},"t":171.188,"s":[170.375,227.375]},{"i":{"x":[0.667,0.667],"y":[1,1]},"o":{"x":[0.333,0.333],"y":[0,0]},"t":187.223,"s":[170.375,422.049]},{"i":{"x":[0.833,0.833],"y":[1,0.833]},"o":{"x":[0.333,0.333],"y":[0,0]},"t":201.066,"s":[170.375,243.375]},{"i":{"x":[0.833,0.833],"y":[0.833,0.833]},"o":{"x":[0.167,0.167],"y":[0.167,0.167]},"t":215.516,"s":[170.375,440.375]},{"i":{"x":[0.667,0.667],"y":[1,1]},"o":{"x":[0.167,0.167],"y":[0,0.167]},"t":225.969,"s":[170.375,440.375]},{"i":{"x":[0.667,0.667],"y":[1,1]},"o":{"x":[0.333,0.333],"y":[0,0]},"t":230.943,"s":[170.375,257.375]},{"i":{"x":[0.667,0.667],"y":[1,1]},"o":{"x":[0.333,0.333],"y":[0,0]},"t":245,"s":[170.375,417.375]},{"i":{"x":[0.667,0.667],"y":[1,1]},"o":{"x":[0.333,0.333],"y":[0,0]},"t":260.816,"s":[170.375,204.375]},{"i":{"x":[0.667,0.667],"y":[1,1]},"o":{"x":[0.333,0.333],"y":[0,0]},"t":276.252,"s":[170.375,420.375]},{"i":{"x":[0.667,0.667],"y":[1,1]},"o":{"x":[0.333,0.333],"y":[0,0]},"t":290.693,"s":[170.375,215.375]},{"i":{"x":[0.833,0.833],"y":[1,0.833]},"o":{"x":[0.333,0.333],"y":[0,0]},"t":305.633,"s":[170.375,353.375]},{"i":{"x":[0.833,0.833],"y":[0.833,0.833]},"o":{"x":[0.167,0.167],"y":[0.167,0.167]},"t":320.941,"s":[170.375,221.317]},{"i":{"x":[0.667,0.667],"y":[1,1]},"o":{"x":[0.167,0.167],"y":[0,0.167]},"t":330.861,"s":[170.375,221.317]},{"i":{"x":[0.667,0.667],"y":[1,1]},"o":{"x":[0.333,0.333],"y":[0,0]},"t":335.84,"s":[170.375,476.375]},{"i":{"x":[0.667,0.667],"y":[1,1]},"o":{"x":[0.333,0.333],"y":[0,0]},"t":350.445,"s":[170.375,229.375]},{"i":{"x":[0.667,0.667],"y":[1,1]},"o":{"x":[0.333,0.333],"y":[0,0]},"t":365.633,"s":[170.375,450.375]},{"i":{"x":[0.667,0.667],"y":[1,1]},"o":{"x":[0.333,0.333],"y":[0,0]},"t":380,"s":[170.375,170.375]},{"i":{"x":[0.667,0.667],"y":[1,1]},"o":{"x":[0.333,0.333],"y":[0,0]},"t":395.428,"s":[170.375,442.375]},{"i":{"x":[0.667,0.667],"y":[1,1]},"o":{"x":[0.333,0.333],"y":[0,0]},"t":410.326,"s":[170.375,238.375]},{"i":{"x":[0.833,0.833],"y":[1,0.833]},"o":{"x":[0.333,0.333],"y":[0,0]},"t":425.223,"s":[170.375,449.375]},{"i":{"x":[0.833,0.833],"y":[0.833,0.833]},"o":{"x":[0.167,0.167],"y":[0.167,0.167]},"t":440.119,"s":[170.375,229.375]},{"i":{"x":[0.667,0.667],"y":[1,1]},"o":{"x":[0.167,0.167],"y":[0,0.167]},"t":448.039,"s":[170.375,229.375]},{"i":{"x":[0.833,0.833],"y":[1,1]},"o":{"x":[0.333,0.333],"y":[0,0]},"t":455.018,"s":[170.375,405.215]},{"t":470,"s":[170.375,170.375]}],"ix":2},"p":{"a":0,"k":[0,0],"ix":3},"r":{"a":0,"k":245,"ix":4},"nm":"Rectangle Path 1","mn":"ADBE Vector Shape - Rect","hd":false},{"ty":"fl","c":{"a":0,"k":[0.984283447266,0.988220214844,0.984283447266,1],"ix":4},"o":{"a":0,"k":100,"ix":5},"r":1,"bm":0,"nm":"Fill 1","mn":"ADBE Vector Graphic - Fill","hd":false},{"ty":"tr","p":{"a":0,"k":[0.691,-58],"ix":2},"a":{"a":0,"k":[0,0],"ix":1},"s":{"a":0,"k":[96.631,96.631],"ix":3},"r":{"a":0,"k":0,"ix":6},"o":{"a":0,"k":100,"ix":7},"sk":{"a":0,"k":0,"ix":4},"sa":{"a":0,"k":0,"ix":5},"nm":"Transform"}],"nm":"Rectangle 1","np":3,"cix":2,"bm":0,"ix":1,"mn":"ADBE Vector Group","hd":false}],"ip":-3,"op":599,"st":-1,"bm":0},{"ddd":0,"ind":2,"ty":4,"nm":"Volume M","sr":1,"ks":{"o":{"a":0,"k":100,"ix":11},"r":{"a":0,"k":0,"ix":10},"p":{"a":0,"k":[750.691,692,0],"ix":2},"a":{"a":0,"k":[0.691,-58,0],"ix":1},"s":{"a":0,"k":[100,100,100],"ix":6}},"ao":0,"shapes":[{"ty":"gr","it":[{"ty":"rc","d":1,"s":{"a":1,"k":[{"i":{"x":[0.667,0.667],"y":[1,1]},"o":{"x":[0.319,0.319],"y":[0,0]},"t":-10,"s":[170.375,655.375]},{"i":{"x":[0.78,0.78],"y":[1,0.835]},"o":{"x":[0.333,0.333],"y":[0,0]},"t":10,"s":[170.375,655.375]},{"i":{"x":[0.667,0.667],"y":[1,1]},"o":{"x":[0.385,0.385],"y":[0,-0.279]},"t":26.236,"s":[170.375,170.375]},{"i":{"x":[0.833,0.833],"y":[1,1]},"o":{"x":[0.333,0.333],"y":[0,0]},"t":41.561,"s":[170.375,645.375]},{"i":{"x":[0.667,0.667],"y":[1,1]},"o":{"x":[0.167,0.167],"y":[0,0.167]},"t":48.916,"s":[170.375,645.375]},{"i":{"x":[0.667,0.667],"y":[1,1]},"o":{"x":[0.333,0.333],"y":[0,0]},"t":56.498,"s":[170.375,322.375]},{"i":{"x":[0.667,0.667],"y":[1,1]},"o":{"x":[0.333,0.333],"y":[0,0]},"t":70.65,"s":[170.375,665.375]},{"i":{"x":[0.667,0.667],"y":[1,1]},"o":{"x":[0.333,0.333],"y":[0,0]},"t":86.629,"s":[170.375,277.375]},{"i":{"x":[0.667,0.667],"y":[1,1]},"o":{"x":[0.333,0.333],"y":[0,0]},"t":100.891,"s":[170.375,674.375]},{"i":{"x":[0.667,0.667],"y":[1,1]},"o":{"x":[0.333,0.333],"y":[0,0]},"t":116.01,"s":[170.375,294.375]},{"i":{"x":[0.667,0.667],"y":[1,1]},"o":{"x":[0.333,0.333],"y":[0,0]},"t":127.35,"s":[170.375,668.375]},{"i":{"x":[0.667,0.667],"y":[1,1]},"o":{"x":[0.333,0.333],"y":[0,0]},"t":145.805,"s":[170.375,263.339]},{"i":{"x":[0.667,0.667],"y":[1,1]},"o":{"x":[0.333,0.333],"y":[0,0]},"t":160.652,"s":[170.375,660.375]},{"i":{"x":[0.833,0.833],"y":[1,0.833]},"o":{"x":[0.333,0.333],"y":[0,0]},"t":176,"s":[170.375,486.375]},{"i":{"x":[0.667,0.667],"y":[1,1]},"o":{"x":[0.167,0.167],"y":[0,0.167]},"t":192.555,"s":[170.375,701.375]},{"i":{"x":[0.833,0.833],"y":[1,0.833]},"o":{"x":[0.333,0.333],"y":[0,0]},"t":205.395,"s":[170.375,279.375]},{"i":{"x":[0.833,0.833],"y":[0.833,0.833]},"o":{"x":[0.167,0.167],"y":[0.167,0.167]},"t":214,"s":[170.375,635.375]},{"i":{"x":[0.833,0.833],"y":[0.833,0.833]},"o":{"x":[0.167,0.167],"y":[0.167,0.167]},"t":220.402,"s":[170.375,635.375]},{"i":{"x":[0.667,0.667],"y":[1,1]},"o":{"x":[0.167,0.167],"y":[0,0.167]},"t":235.188,"s":[170.375,293.375]},{"i":{"x":[0.833,0.833],"y":[1,0.833]},"o":{"x":[0.333,0.333],"y":[0,0]},"t":250.086,"s":[170.375,612.375]},{"i":{"x":[0.667,0.667],"y":[1,1]},"o":{"x":[0.167,0.167],"y":[0,0.167]},"t":265.215,"s":[170.375,286.375]},{"i":{"x":[0.667,0.667],"y":[1,1]},"o":{"x":[0.333,0.333],"y":[0,0]},"t":280,"s":[170.375,613.375]},{"i":{"x":[0.667,0.667],"y":[1,1]},"o":{"x":[0.333,0.333],"y":[0,0]},"t":295.557,"s":[170.375,186.375]},{"i":{"x":[0.667,0.667],"y":[1,1]},"o":{"x":[0.333,0.333],"y":[0,0]},"t":310.033,"s":[170.375,457.375]},{"i":{"x":[0.667,0.667],"y":[1,1]},"o":{"x":[0.333,0.333],"y":[0,0]},"t":324.969,"s":[170.375,296.375]},{"i":{"x":[0.667,0.667],"y":[1,1]},"o":{"x":[0.333,0.333],"y":[0,0]},"t":339.908,"s":[170.375,648.375]},{"i":{"x":[0.667,0.667],"y":[1,1]},"o":{"x":[0.333,0.333],"y":[0,0]},"t":347.529,"s":[170.375,648.375]},{"i":{"x":[0.667,0.667],"y":[1,1]},"o":{"x":[0.333,0.333],"y":[0,0]},"t":354.846,"s":[170.375,325.375]},{"i":{"x":[0.667,0.667],"y":[1,1]},"o":{"x":[0.333,0.333],"y":[0,0]},"t":369.785,"s":[170.375,629.375]},{"i":{"x":[0.667,0.667],"y":[1,1]},"o":{"x":[0.333,0.333],"y":[0,0]},"t":384.385,"s":[170.375,247.375]},{"i":{"x":[0.667,0.667],"y":[1,1]},"o":{"x":[0.333,0.333],"y":[0,0]},"t":400.203,"s":[170.375,658.257]},{"i":{"x":[0.667,0.667],"y":[1,1]},"o":{"x":[0.333,0.333],"y":[0,0]},"t":415.102,"s":[170.375,301.375]},{"i":{"x":[0.667,0.667],"y":[1,1]},"o":{"x":[0.333,0.333],"y":[0,0]},"t":430,"s":[170.375,646.375]},{"i":{"x":[0.667,0.667],"y":[1,1]},"o":{"x":[0.333,0.333],"y":[0,0]},"t":444.895,"s":[170.375,287.375]},{"i":{"x":[0.78,0.78],"y":[1,0.841]},"o":{"x":[0.333,0.333],"y":[0,0]},"t":459.414,"s":[170.375,655.375]},{"t":475,"s":[170.375,170.375]}],"ix":2},"p":{"a":0,"k":[0,0],"ix":3},"r":{"a":0,"k":245,"ix":4},"nm":"Rectangle Path 1","mn":"ADBE Vector Shape - Rect","hd":false},{"ty":"fl","c":{"a":0,"k":[0.984283447266,0.988220214844,0.984283447266,1],"ix":4},"o":{"a":0,"k":100,"ix":5},"r":1,"bm":0,"nm":"Fill 1","mn":"ADBE Vector Graphic - Fill","hd":false},{"ty":"tr","p":{"a":0,"k":[0.691,-58],"ix":2},"a":{"a":0,"k":[0,0],"ix":1},"s":{"a":0,"k":[96.631,96.631],"ix":3},"r":{"a":0,"k":0,"ix":6},"o":{"a":0,"k":100,"ix":7},"sk":{"a":0,"k":0,"ix":4},"sa":{"a":0,"k":0,"ix":5},"nm":"Transform"}],"nm":"Rectangle 1","np":3,"cix":2,"bm":0,"ix":1,"mn":"ADBE Vector Group","hd":false}],"ip":-5,"op":599,"st":-5,"bm":0},{"ddd":0,"ind":3,"ty":4,"nm":"Volume R","sr":1,"ks":{"o":{"a":0,"k":100,"ix":11},"r":{"a":0,"k":0,"ix":10},"p":{"a":0,"k":[992.691,692,0],"ix":2},"a":{"a":0,"k":[0.691,-58,0],"ix":1},"s":{"a":0,"k":[100,100,100],"ix":6}},"ao":0,"shapes":[{"ty":"gr","it":[{"ty":"rc","d":1,"s":{"a":1,"k":[{"i":{"x":[0.667,0.667],"y":[1,1]},"o":{"x":[0.333,0.333],"y":[0,0]},"t":17.906,"s":[170.375,170.375]},{"i":{"x":[0.667,0.667],"y":[1,1]},"o":{"x":[0.333,0.333],"y":[0,0]},"t":33,"s":[170.375,386.453]},{"i":{"x":[0.667,0.667],"y":[1,1]},"o":{"x":[0.333,0.333],"y":[0,0]},"t":47.74,"s":[170.375,235.375]},{"i":{"x":[0.667,0.667],"y":[1,1]},"o":{"x":[0.333,0.333],"y":[0,0]},"t":63,"s":[170.375,382.278]},{"i":{"x":[0.667,0.667],"y":[1,1]},"o":{"x":[0.333,0.333],"y":[0,0]},"t":77.615,"s":[170.375,229.375]},{"i":{"x":[0.667,0.667],"y":[1,1]},"o":{"x":[0.333,0.333],"y":[0,0]},"t":92,"s":[170.375,420.618]},{"i":{"x":[0.667,0.667],"y":[1,1]},"o":{"x":[0.333,0.333],"y":[0,0]},"t":107.291,"s":[170.375,257.131]},{"i":{"x":[0.667,0.667],"y":[1,1]},"o":{"x":[0.333,0.333],"y":[0,0]},"t":122,"s":[170.375,393.7]},{"i":{"x":[0.833,0.833],"y":[1,0.833]},"o":{"x":[0.333,0.333],"y":[0,0]},"t":137.369,"s":[170.375,260.375]},{"i":{"x":[0.833,0.833],"y":[0.833,0.833]},"o":{"x":[0.167,0.167],"y":[0.167,0.167]},"t":152,"s":[170.375,347.19]},{"i":{"x":[0.833,0.833],"y":[0.833,0.833]},"o":{"x":[0.167,0.167],"y":[0.167,0.167]},"t":161.543,"s":[170.375,490.375]},{"i":{"x":[0.667,0.667],"y":[1,1]},"o":{"x":[0.167,0.167],"y":[0,0.167]},"t":162,"s":[170.375,347.19]},{"i":{"x":[0.667,0.667],"y":[1,1]},"o":{"x":[0.333,0.333],"y":[0,0]},"t":167,"s":[170.375,214.222]},{"i":{"x":[0.667,0.667],"y":[1,1]},"o":{"x":[0.333,0.333],"y":[0,0]},"t":182,"s":[170.375,381.711]},{"i":{"x":[0.667,0.667],"y":[1,1]},"o":{"x":[0.333,0.333],"y":[0,0]},"t":197.121,"s":[170.375,243.375]},{"i":{"x":[0.667,0.667],"y":[1,1]},"o":{"x":[0.333,0.333],"y":[0,0]},"t":212,"s":[170.375,425.586]},{"i":{"x":[0.667,0.667],"y":[1,1]},"o":{"x":[0.333,0.333],"y":[0,0]},"t":226.467,"s":[170.375,263.375]},{"i":{"x":[0.833,0.833],"y":[1,0.833]},"o":{"x":[0.333,0.333],"y":[0,0]},"t":241,"s":[170.375,439.063]},{"i":{"x":[0.833,0.833],"y":[0.833,0.833]},"o":{"x":[0.167,0.167],"y":[0.167,0.167]},"t":256.869,"s":[170.375,268.375]},{"i":{"x":[0.667,0.667],"y":[1,1]},"o":{"x":[0.167,0.167],"y":[0,0.167]},"t":266.438,"s":[170.375,268.375]},{"i":{"x":[0.667,0.667],"y":[1,1]},"o":{"x":[0.333,0.333],"y":[0,0]},"t":272.307,"s":[170.375,428.892]},{"i":{"x":[0.667,0.667],"y":[1,1]},"o":{"x":[0.333,0.333],"y":[0,0]},"t":286.748,"s":[170.375,250.375]},{"i":{"x":[0.667,0.667],"y":[1,1]},"o":{"x":[0.333,0.333],"y":[0,0]},"t":302,"s":[170.375,327.639]},{"i":{"x":[0.667,0.667],"y":[1,1]},"o":{"x":[0.333,0.333],"y":[0,0]},"t":316.625,"s":[170.375,235.375]},{"i":{"x":[0.667,0.667],"y":[1,1]},"o":{"x":[0.333,0.333],"y":[0,0]},"t":332,"s":[170.375,359.199]},{"i":{"x":[0.667,0.667],"y":[1,1]},"o":{"x":[0.333,0.333],"y":[0,0]},"t":346.5,"s":[170.375,227.375]},{"i":{"x":[0.833,0.833],"y":[1,0.833]},"o":{"x":[0.333,0.333],"y":[0,0]},"t":361.689,"s":[170.375,409.375]},{"i":{"x":[0.833,0.833],"y":[0.833,0.833]},"o":{"x":[0.167,0.167],"y":[0.167,0.167]},"t":376.055,"s":[170.375,188.143]},{"i":{"x":[0.667,0.667],"y":[1,1]},"o":{"x":[0.167,0.167],"y":[0,0.167]},"t":385.506,"s":[170.375,188.143]},{"i":{"x":[0.667,0.667],"y":[1,1]},"o":{"x":[0.333,0.333],"y":[0,0]},"t":391.482,"s":[170.375,450.375]},{"i":{"x":[0.667,0.667],"y":[1,1]},"o":{"x":[0.333,0.333],"y":[0,0]},"t":406.381,"s":[170.375,238.375]},{"i":{"x":[0.667,0.667],"y":[1,1]},"o":{"x":[0.333,0.333],"y":[0,0]},"t":421.279,"s":[170.375,463.375]},{"i":{"x":[0.667,0.667],"y":[1,1]},"o":{"x":[0.333,0.333],"y":[0,0]},"t":436.176,"s":[170.375,226.375]},{"i":{"x":[0.833,0.833],"y":[1,1]},"o":{"x":[0.333,0.333],"y":[0,0]},"t":451,"s":[170.375,394.186]},{"t":466,"s":[170.375,170.375]}],"ix":2},"p":{"a":0,"k":[0,0],"ix":3},"r":{"a":0,"k":245,"ix":4},"nm":"Rectangle Path 1","mn":"ADBE Vector Shape - Rect","hd":false},{"ty":"fl","c":{"a":0,"k":[0.984283447266,0.988220214844,0.984283447266,1],"ix":4},"o":{"a":0,"k":100,"ix":5},"r":1,"bm":0,"nm":"Fill 1","mn":"ADBE Vector Graphic - Fill","hd":false},{"ty":"tr","p":{"a":0,"k":[0.691,-58],"ix":2},"a":{"a":0,"k":[0,0],"ix":1},"s":{"a":0,"k":[96.631,96.631],"ix":3},"r":{"a":0,"k":0,"ix":6},"o":{"a":0,"k":100,"ix":7},"sk":{"a":0,"k":0,"ix":4},"sa":{"a":0,"k":0,"ix":5},"nm":"Transform"}],"nm":"Rectangle 1","np":3,"cix":2,"bm":0,"ix":1,"mn":"ADBE Vector Group","hd":false}],"ip":-5,"op":595,"st":-5,"bm":0},{"ddd":0,"ind":7,"ty":4,"nm":"Logo Bubble Outlines","sr":1,"ks":{"o":{"a":0,"k":100,"ix":11},"r":{"a":0,"k":0,"ix":10},"p":{"a":0,"k":[730,782,0],"ix":2},"a":{"a":0,"k":[702.5,702.5,0],"ix":1},"s":{"a":0,"k":[108,108,100],"ix":6}},"ao":0,"shapes":[{"ty":"gr","it":[{"ind":0,"ty":"sh","ix":1,"ks":{"a":0,"k":{"i":[[-58.017,4.424],[-92.696,-126.256],[19.45,-114.426],[111.36,-65.801],[115.871,33.87],[15.115,6.22],[39.636,-11.54],[41.271,-13.87],[-2.5,13.5],[-13.33,39.989],[3.827,33.898],[2.474,8.897],[-18.425,87.238],[-113.394,61.879]],"o":[[157.637,-5.589],[64.12,96.241],[-26.3,127.199],[-106.129,57.2],[-15.551,-5.11],[-39.697,-10.88],[-41.396,13.47],[-13.5,2.5],[13.337,-40.01],[9.827,-32.768],[-1.526,-9.103],[-33.091,-82.762],[30.939,-125.788],[51.983,-26.576]],"v":[[-23.102,-423.363],[352.398,-242.363],[419.398,73.637],[212.898,363.137],[-120.102,398.137],[-166.102,381.137],[-285.102,382.137],[-409.102,423.137],[-425.602,406.637],[-385.602,286.637],[-376.602,186.637],[-382.602,159.637],[-404.602,-95.363],[-188.102,-376.863]],"c":true},"ix":2},"nm":"Path 1","mn":"ADBE Vector Shape - Group","hd":false},{"ty":"fl","c":{"a":0,"k":[0.364705882353,0.403921598547,0.921568687289,1],"ix":4},"o":{"a":0,"k":100,"ix":5},"r":1,"bm":0,"nm":"Fill 1","mn":"ADBE Vector Graphic - Fill","hd":false},{"ty":"tr","p":{"a":0,"k":[713.602,638.863],"ix":2},"a":{"a":0,"k":[0,0],"ix":1},"s":{"a":0,"k":[100,100],"ix":3},"r":{"a":0,"k":0,"ix":6},"o":{"a":0,"k":100,"ix":7},"sk":{"a":0,"k":0,"ix":4},"sa":{"a":0,"k":0,"ix":5},"nm":"Transform"}],"nm":"Group 1","np":4,"cix":2,"bm":0,"ix":1,"mn":"ADBE Vector Group","hd":false}],"ip":0,"op":600,"st":0,"bm":0}],"markers":[]}